Metadata-Version: 1.0
Name: conntest
Version: 2.0.2.post1
Summary: Try to connect to a host via SSH/RDP/VNC/VMware vCenter auth etc
Home-page: https://github.com/pschmitt/conntest
Author: Philipp Schmitt
Author-email: philipp@schmitt.co
License: GPL3
Platform: UNKNOWN
